forktex/__init__.py
forktex-0.1.3.dist-info/METADATA
forktex-0.1.3.dist-info/WHEEL
forktex-0.1.3.dist-info/RECORD
