Metadata-Version: 2.3
Name: forktex
Version: 0.1.3
Summary: Official Python library to interact with Forktex API
Author: Alex Doc
Author-email: alexandru.dochian@forktex.com
Requires-Python: >=3.11
Classifier: Programming Language :: Python :: 3
Classifier: Programming Language :: Python :: 3.11
Classifier: Programming Language :: Python :: 3.12
Classifier: Programming Language :: Python :: 3.13
Project-URL: Bug Tracker, https://github.com/forktex/forktex-python/issues
Project-URL: Homepage, https://forktex.com
Project-URL: Repository, https://github.com/forktex/forktex-python
